{"cameraMode":{"drawMode":0,"name":"Shaded","section":"Shading Mode"},"sceneLighting":true,"audioPlay":false,"sceneViewState":{"m_AlwaysRefresh":false,"showFog":true,"showSkybox":true,"showFlares":true,"showImageEffects":true,"showParticleSystems":true,"showVisualEffectGraphs":true,"m_FxEnabled":true},"in2DMode":false,"pivot":{"x":-15.821786880493164,"y":-2.4430904388427736,"z":-5.220192909240723},"rotation":{"x":0.11216991394758225,"y":-0.7456970810890198,"z":0.1299242377281189,"w":0.6437988877296448},"size":20.177865982055665,"orthographic":false}